tdlib_python/__init__.py
tdlib_python/tdlib_python.py
tdlib_python/zeroun_intezar_agler/__init__.py
tdlib_python/zeroun_intezar_agler/zeroun_intezar_agler.py
tdlib_python-0.0.2.dist-info/licenses/LICENSE
tdlib_python-0.0.2.dist-info/METADATA
tdlib_python-0.0.2.dist-info/WHEEL
tdlib_python-0.0.2.dist-info/top_level.txt
tdlib_python-0.0.2.dist-info/RECORD
