Metadata-Version: 2.4
Name: tdlib-python
Version: 0.0.2
Summary: tdlib_python ZerounIntezarAgler
Author: zerounintezaragler
Project-URL: homepage, https://github.com/zerounintezaragler/tdlib_python
Project-URL: repository, https://github.com/zerounintezaragler/tdlib_python
Project-URL: documentation, https://github.com/zerounintezaragler/tdlib_python
License-File: LICENSE
Dynamic: license-file
